[{"rikishiId":"1190","shikona":"Kaonishiki","rank":"Sandanme 25","wins":7,"losses":0,"winPercentage":1,"kimariteBreakdown":[{"kimariteId":"yorikiri","count":4},{"kimariteId":"oshidashi","count":2},{"kimariteId":"okuridashi","count":1}]},{"rikishiId":"7171","shikona":"Ryuseiyama","rank":"Sandanme 16","wins":6,"losses":1,"winPercentage":0.8571,"kimariteBreakdown":[{"kimariteId":"hatakikomi","count":4},{"kimariteId":"yorikiri","count":1},{"kimariteId":"oshidashi","count":1}]},{"rikishiId":"12284","shikona":"Izumigawa","rank":"Sandanme 34","wins":6,"losses":1,"winPercentage":0.8571,"kimariteBreakdown":[{"kimariteId":"oshidashi","count":4},{"kimariteId":"uwatenage","count":1},{"kimariteId":"yorikiri","count":1}]},{"rikishiId":"12209","shikona":"Kenshin","rank":"Sandanme 40","wins":6,"losses":1,"winPercentage":0.8571,"kimariteBreakdown":[{"kimariteId":"hatakikomi","count":3},{"kimariteId":"oshidashi","count":1},{"kimariteId":"hikiotoshi","count":1},{"kimariteId":"tsukiotoshi","count":1}]},{"rikishiId":"1053","shikona":"Kasugakuni","rank":"Sandanme 51","wins":6,"losses":1,"winPercentage":0.8571,"kimariteBreakdown":[{"kimariteId":"yorikiri","count":5},{"kimariteId":"oshidashi","count":1}]},{"rikishiId":"12027","shikona":"Mihamaumi","rank":"Sandanme 65","wins":6,"losses":1,"winPercentage":0.8571,"kimariteBreakdown":[{"kimariteId":"oshidashi","count":2},{"kimariteId":"hatakikomi","count":2},{"kimariteId":"shitatenage","count":1},{"kimariteId":"kotenage","count":1}]},{"rikishiId":"11948","shikona":"Kotozensho","rank":"Sandanme 66","wins":6,"losses":1,"winPercentage":0.8571,"kimariteBreakdown":[{"kimariteId":"tsukidashi","count":1},{"kimariteId":"hikkake","count":1},{"kimariteId":"hatakikomi","count":1},{"kimariteId":"okuridashi","count":1},{"kimariteId":"yorikiri","count":1},{"kimariteId":"oshidashi","count":1}]},{"rikishiId":"12388","shikona":"Chiyotaiho","rank":"Sandanme 84","wins":6,"losses":1,"winPercentage":0.8571,"kimariteBreakdown":[{"kimariteId":"yorikiri","count":3},{"kimariteId":"oshidashi","count":2},{"kimariteId":"shitatehineri","count":1}]},{"rikishiId":"9126","shikona":"Hirose","rank":"Sandanme 89","wins":6,"losses":1,"winPercentage":0.8571,"kimariteBreakdown":[{"kimariteId":"yorikiri","count":3},{"kimariteId":"oshidashi","count":2},{"kimariteId":"shitatehineri","count":1}]},{"rikishiId":"12335","shikona":"Kurahashi","rank":"Sandanme 3","wins":5,"losses":1,"winPercentage":0.8333,"kimariteBreakdown":[{"kimariteId":"oshidashi","count":3},{"kimariteId":"yorikiri","count":1},{"kimariteId":"oshitaoshi","count":1}]},{"rikishiId":"335","shikona":"Shoketsu","rank":"Sandanme 7","wins":5,"losses":2,"winPercentage":0.7143,"kimariteBreakdown":[{"kimariteId":"yorikiri","count":3},{"kimariteId":"oshitaoshi","count":1},{"kimariteId":"hikiotoshi","count":1}]},{"rikishiId":"6521","shikona":"Wakanofuji","rank":"Sandanme 9","wins":5,"losses":2,"winPercentage":0.7143,"kimariteBreakdown":[{"kimariteId":"yorikiri","count":2},{"kimariteId":"hatakikomi","count":1},{"kimariteId":"uwatenage","count":1},{"kimariteId":"hikkake","count":1}]},{"rikishiId":"12059","shikona":"Daishozen","rank":"Sandanme 13","wins":5,"losses":2,"winPercentage":0.7143,"kimariteBreakdown":[{"kimariteId":"hatakikomi","count":2},{"kimariteId":"yorikiri","count":1},{"kimariteId":"okuridashi","count":1},{"kimariteId":"tsukiotoshi","count":1}]},{"rikishiId":"12086","shikona":"Okinohama","rank":"Sandanme 18","wins":5,"losses":2,"winPercentage":0.7143,"kimariteBreakdown":[{"kimariteId":"yoritaoshi","count":1},{"kimariteId":"oshidashi","count":1},{"kimariteId":"yorikiri","count":1},{"kimariteId":"shitatenage","count":1},{"kimariteId":"hikkake","count":1}]},{"rikishiId":"9087","shikona":"Kanryu","rank":"Sandanme 21","wins":5,"losses":2,"winPercentage":0.7143,"kimariteBreakdown":[{"kimariteId":"oshidashi","count":2},{"kimariteId":"yorikiri","count":2},{"kimariteId":"kimedashi","count":1}]},{"rikishiId":"296","shikona":"Yoshiazuma","rank":"Sandanme 23","wins":5,"losses":2,"winPercentage":0.7143,"kimariteBreakdown":[{"kimariteId":"oshidashi","count":2},{"kimariteId":"yorikiri","count":2},{"kimariteId":"tsukidashi","count":1}]},{"rikishiId":"300","shikona":"Dairaido","rank":"Sandanme 28","wins":5,"losses":2,"winPercentage":0.7143,"kimariteBreakdown":[{"kimariteId":"tsukidashi","count":2},{"kimariteId":"yorikiri","count":1},{"kimariteId":"hatakikomi","count":1},{"kimariteId":"tsukiotoshi","count":1}]},{"rikishiId":"12074","shikona":"Toshoyama","rank":"Sandanme 29","wins":5,"losses":2,"winPercentage":0.7143,"kimariteBreakdown":[{"kimariteId":"oshidashi","count":3},{"kimariteId":"yorikiri","count":1},{"kimariteId":"shitatenage","count":1}]},{"rikishiId":"6009","shikona":"Sadanokuni","rank":"Sandanme 31","wins":5,"losses":2,"winPercentage":0.7143,"kimariteBreakdown":[{"kimariteId":"yorikiri","count":2},{"kimariteId":"tsukiotoshi","count":2},{"kimariteId":"oshidashi","count":1}]},{"rikishiId":"523","shikona":"Gorikiyama","rank":"Sandanme 38","wins":5,"losses":2,"winPercentage":0.7143,"kimariteBreakdown":[{"kimariteId":"oshidashi","count":2},{"kimariteId":"tsukiotoshi","count":1},{"kimariteId":"hikiotoshi","count":1},{"kimariteId":"yorikiri","count":1}]},{"rikishiId":"7116","shikona":"Daijo","rank":"Sandanme 39","wins":5,"losses":2,"winPercentage":0.7143,"kimariteBreakdown":[{"kimariteId":"oshidashi","count":1},{"kimariteId":"okuridashi","count":1},{"kimariteId":"yorikiri","count":1},{"kimariteId":"tsukidashi","count":1},{"kimariteId":"kotenage","count":1}]},{"rikishiId":"12261","shikona":"Asadaimon","rank":"Sandanme 42","wins":5,"losses":2,"winPercentage":0.7143,"kimariteBreakdown":[{"kimariteId":"oshidashi","count":2},{"kimariteId":"tsukiotoshi","count":2},{"kimariteId":"hatakikomi","count":1}]},{"rikishiId":"11992","shikona":"Oisato","rank":"Sandanme 46","wins":5,"losses":2,"winPercentage":0.7143,"kimariteBreakdown":[{"kimariteId":"tsukiotoshi","count":2},{"kimariteId":"oshidashi","count":1},{"kimariteId":"oshitaoshi","count":1},{"kimariteId":"yorikiri","count":1}]},{"rikishiId":"7124","shikona":"Kayatoiwa","rank":"Sandanme 49","wins":5,"losses":2,"winPercentage":0.7143,"kimariteBreakdown":[{"kimariteId":"yorikiri","count":3},{"kimariteId":"hikiotoshi","count":1},{"kimariteId":"oshidashi","count":1}]},{"rikishiId":"12103","shikona":"Wakakinsho","rank":"Sandanme 50","wins":5,"losses":2,"winPercentage":0.7143,"kimariteBreakdown":[{"kimariteId":"oshidashi","count":3},{"kimariteId":"yorikiri","count":2}]},{"rikishiId":"7151","shikona":"Kotofukujuno","rank":"Sandanme 57","wins":5,"losses":2,"winPercentage":0.7143,"kimariteBreakdown":[{"kimariteId":"oshidashi","count":2},{"kimariteId":"yorikiri","count":2},{"kimariteId":"uwatenage","count":1}]},{"rikishiId":"6530","shikona":"Haruhikari","rank":"Sandanme 58","wins":5,"losses":2,"winPercentage":0.7143,"kimariteBreakdown":[{"kimariteId":"yorikiri","count":2},{"kimariteId":"oshidashi","count":1},{"kimariteId":"hikiotoshi","count":1},{"kimariteId":"tsukiotoshi","count":1}]},{"rikishiId":"1010","shikona":"Asanotosa","rank":"Sandanme 63","wins":5,"losses":2,"winPercentage":0.7143,"kimariteBreakdown":[{"kimariteId":"hatakikomi","count":2},{"kimariteId":"oshidashi","count":1},{"kimariteId":"yorikiri","count":1},{"kimariteId":"tsukiotoshi","count":1}]},{"rikishiId":"12461","shikona":"Kamitani","rank":"Sandanme 66","wins":5,"losses":2,"winPercentage":0.7143,"kimariteBreakdown":[{"kimariteId":"oshidashi","count":2},{"kimariteId":"yorikiri","count":2},{"kimariteId":"oshitaoshi","count":1}]},{"rikishiId":"9092","shikona":"Sumanoumi","rank":"Sandanme 70","wins":5,"losses":2,"winPercentage":0.7143,"kimariteBreakdown":[{"kimariteId":"oshidashi","count":2},{"kimariteId":"yorikiri","count":2},{"kimariteId":"hatakikomi","count":1}]},{"rikishiId":"12384","shikona":"Kotonofuji","rank":"Sandanme 73","wins":5,"losses":2,"winPercentage":0.7143,"kimariteBreakdown":[{"kimariteId":"oshidashi","count":3},{"kimariteId":"shitatenage","count":1},{"kimariteId":"tsukiotoshi","count":1}]},{"rikishiId":"11744","shikona":"Hokuyozan","rank":"Sandanme 76","wins":5,"losses":2,"winPercentage":0.7143,"kimariteBreakdown":[{"kimariteId":"oshidashi","count":2},{"kimariteId":"tsukidashi","count":1},{"kimariteId":"oshitaoshi","count":1},{"kimariteId":"yorikiri","count":1}]},{"rikishiId":"12120","shikona":"Meiko","rank":"Sandanme 77","wins":5,"losses":2,"winPercentage":0.7143,"kimariteBreakdown":[{"kimariteId":"yorikiri","count":3},{"kimariteId":"yoritaoshi","count":1},{"kimariteId":"oshidashi","count":1}]},{"rikishiId":"12085","shikona":"Fujinotani","rank":"Sandanme 80","wins":5,"losses":2,"winPercentage":0.7143,"kimariteBreakdown":[{"kimariteId":"yorikiri","count":2},{"kimariteId":"kotenage","count":1},{"kimariteId":"kainahineri","count":1},{"kimariteId":"uwatenage","count":1}]},{"rikishiId":"1408","shikona":"Daishokaku","rank":"Sandanme 85","wins":5,"losses":2,"winPercentage":0.7143,"kimariteBreakdown":[{"kimariteId":"uwatenage","count":3},{"kimariteId":"oshidashi","count":1},{"kimariteId":"hatakikomi","count":1}]},{"rikishiId":"800","shikona":"Hienriki","rank":"Sandanme 86","wins":5,"losses":2,"winPercentage":0.7143,"kimariteBreakdown":[{"kimariteId":"oshidashi","count":3},{"kimariteId":"yorikiri","count":2}]},{"rikishiId":"11989","shikona":"Daikiho","rank":"Sandanme 89","wins":5,"losses":2,"winPercentage":0.7143,"kimariteBreakdown":[{"kimariteId":"oshidashi","count":2},{"kimariteId":"yorikiri","count":1},{"kimariteId":"hatakikomi","count":1},{"kimariteId":"shitatenage","count":1}]},{"rikishiId":"1167","shikona":"Kyokuhozan","rank":"Sandanme 93","wins":5,"losses":2,"winPercentage":0.7143,"kimariteBreakdown":[{"kimariteId":"oshidashi","count":3},{"kimariteId":"hatakikomi","count":1},{"kimariteId":"yorikiri","count":1}]},{"rikishiId":"12450","shikona":"Akikaze","rank":"Sandanme 95","wins":5,"losses":2,"winPercentage":0.7143,"kimariteBreakdown":[{"kimariteId":"tsukiotoshi","count":2},{"kimariteId":"yorikiri","count":1},{"kimariteId":"kotenage","count":1},{"kimariteId":"sotogake","count":1}]},{"rikishiId":"11727","shikona":"Amatsu","rank":"Sandanme 19","wins":4,"losses":1,"winPercentage":0.8,"kimariteBreakdown":[{"kimariteId":"hatakikomi","count":1},{"kimariteId":"katasukashi","count":1},{"kimariteId":"oshidashi","count":1},{"kimariteId":"hikiotoshi","count":1}]},{"rikishiId":"12497","shikona":"Joyuriki","rank":"Sandanme 6","wins":4,"losses":2,"winPercentage":0.6667,"kimariteBreakdown":[{"kimariteId":"yorikiri","count":2},{"kimariteId":"okuritaoshi","count":1},{"kimariteId":"oshitaoshi","count":1}]},{"rikishiId":"12002","shikona":"Kotorikisen","rank":"Sandanme 11","wins":4,"losses":2,"winPercentage":0.6667,"kimariteBreakdown":[{"kimariteId":"oshidashi","count":3},{"kimariteId":"oshitaoshi","count":1}]},{"rikishiId":"12195","shikona":"Kiyonoumi","rank":"Sandanme 21","wins":4,"losses":2,"winPercentage":0.6667,"kimariteBreakdown":[{"kimariteId":"oshidashi","count":2},{"kimariteId":"hikiotoshi","count":1},{"kimariteId":"yorikiri","count":1}]},{"rikishiId":"11977","shikona":"Hokutohomare","rank":"Sandanme 7","wins":4,"losses":3,"winPercentage":0.5714,"kimariteBreakdown":[{"kimariteId":"okuridashi","count":1},{"kimariteId":"oshidashi","count":1},{"kimariteId":"yorikiri","count":1},{"kimariteId":"katasukashi","count":1}]},{"rikishiId":"12435","shikona":"Maikeru","rank":"Sandanme 8","wins":4,"losses":3,"winPercentage":0.5714,"kimariteBreakdown":[{"kimariteId":"hatakikomi","count":1},{"kimariteId":"tsukiotoshi","count":1},{"kimariteId":"sukuinage","count":1},{"kimariteId":"hikiotoshi","count":1}]},{"rikishiId":"6612","shikona":"Aozora","rank":"Sandanme 12","wins":4,"losses":3,"winPercentage":0.5714,"kimariteBreakdown":[{"kimariteId":"oshidashi","count":2},{"kimariteId":"tsukidashi","count":1},{"kimariteId":"hatakikomi","count":1}]},{"rikishiId":"12333","shikona":"Tokunomusashi","rank":"Sandanme 14","wins":4,"losses":3,"winPercentage":0.5714,"kimariteBreakdown":[{"kimariteId":"uwatenage","count":2},{"kimariteId":"hatakikomi","count":1},{"kimariteId":"oshidashi","count":1}]},{"rikishiId":"12041","shikona":"Saidaiji","rank":"Sandanme 15","wins":4,"losses":3,"winPercentage":0.5714,"kimariteBreakdown":[{"kimariteId":"hikiotoshi","count":1},{"kimariteId":"makiotoshi","count":1},{"kimariteId":"oshidashi","count":1},{"kimariteId":"hatakikomi","count":1}]},{"rikishiId":"11993","shikona":"Tsugaruumi","rank":"Sandanme 15","wins":4,"losses":3,"winPercentage":0.5714,"kimariteBreakdown":[{"kimariteId":"yorikiri","count":2},{"kimariteId":"tsukitaoshi","count":1},{"kimariteId":"oshidashi","count":1}]},{"rikishiId":"5964","shikona":"Hitachigo","rank":"Sandanme 22","wins":4,"losses":3,"winPercentage":0.5714,"kimariteBreakdown":[{"kimariteId":"oshidashi","count":1},{"kimariteId":"hatakikomi","count":1},{"kimariteId":"yorikiri","count":1},{"kimariteId":"tsukiotoshi","count":1}]},{"rikishiId":"12272","shikona":"Nakashima","rank":"Sandanme 22","wins":4,"losses":3,"winPercentage":0.5714,"kimariteBreakdown":[{"kimariteId":"yorikiri","count":3},{"kimariteId":"sukuinage","count":1}]},{"rikishiId":"12475","shikona":"Wakazakura","rank":"Sandanme 24","wins":4,"losses":3,"winPercentage":0.5714,"kimariteBreakdown":[{"kimariteId":"sukuinage","count":1},{"kimariteId":"yorikiri","count":1},{"kimariteId":"oshidashi","count":1},{"kimariteId":"hatakikomi","count":1}]},{"rikishiId":"11958","shikona":"Hibikiryu","rank":"Sandanme 24","wins":4,"losses":3,"winPercentage":0.5714,"kimariteBreakdown":[{"kimariteId":"oshidashi","count":2},{"kimariteId":"shitatenage","count":1},{"kimariteId":"yorikiri","count":1}]},{"rikishiId":"12005","shikona":"Seido","rank":"Sandanme 32","wins":4,"losses":3,"winPercentage":0.5714,"kimariteBreakdown":[{"kimariteId":"oshidashi","count":1},{"kimariteId":"oshitaoshi","count":1},{"kimariteId":"hatakikomi","count":1},{"kimariteId":"hikiotoshi","count":1}]},{"rikishiId":"12058","shikona":"Daishoki","rank":"Sandanme 32","wins":4,"losses":3,"winPercentage":0.5714,"kimariteBreakdown":[{"kimariteId":"oshidashi","count":3},{"kimariteId":"uwatenage","count":1}]},{"rikishiId":"12019","shikona":"Kotoryusei","rank":"Sandanme 33","wins":4,"losses":3,"winPercentage":0.5714,"kimariteBreakdown":[{"kimariteId":"oshidashi","count":2},{"kimariteId":"yorikiri","count":1},{"kimariteId":"nichonage","count":1}]},{"rikishiId":"11873","shikona":"Kototora","rank":"Sandanme 33","wins":4,"losses":3,"winPercentage":0.5714,"kimariteBreakdown":[{"kimariteId":"oshidashi","count":1},{"kimariteId":"sukuinage","count":1},{"kimariteId":"yorikiri","count":1},{"kimariteId":"tsukitaoshi","count":1}]},{"rikishiId":"5999","shikona":"Karatsuumi","rank":"Sandanme 35","wins":4,"losses":3,"winPercentage":0.5714,"kimariteBreakdown":[{"kimariteId":"yorikiri","count":2},{"kimariteId":"oshidashi","count":1},{"kimariteId":"okuridashi","count":1}]},{"rikishiId":"12355","shikona":"Hikarifuji","rank":"Sandanme 35","wins":4,"losses":3,"winPercentage":0.5714,"kimariteBreakdown":[{"kimariteId":"yorikiri","count":2},{"kimariteId":"oshidashi","count":2}]},{"rikishiId":"6002","shikona":"Ryuseio","rank":"Sandanme 42","wins":4,"losses":3,"winPercentage":0.5714,"kimariteBreakdown":[{"kimariteId":"yorikiri","count":3},{"kimariteId":"tsukihiza","count":1}]},{"rikishiId":"550","shikona":"Musashiumi","rank":"Sandanme 43","wins":4,"losses":3,"winPercentage":0.5714,"kimariteBreakdown":[{"kimariteId":"oshidashi","count":2},{"kimariteId":"yorikiri","count":1},{"kimariteId":"tsukidashi","count":1}]},{"rikishiId":"12468","shikona":"Kotakiyama","rank":"Sandanme 47","wins":4,"losses":3,"winPercentage":0.5714,"kimariteBreakdown":[{"kimariteId":"yorikiri","count":2},{"kimariteId":"uwatenage","count":1},{"kimariteId":"oshidashi","count":1}]},{"rikishiId":"12465","shikona":"Daishosei","rank":"Sandanme 47","wins":4,"losses":3,"winPercentage":0.5714,"kimariteBreakdown":[{"kimariteId":"uwatenage","count":1},{"kimariteId":"yorikiri","count":1},{"kimariteId":"hatakikomi","count":1},{"kimariteId":"okuridashi","count":1}]},{"rikishiId":"11761","shikona":"Kotorikuzan","rank":"Sandanme 48","wins":4,"losses":3,"winPercentage":0.5714,"kimariteBreakdown":[{"kimariteId":"hatakikomi","count":1},{"kimariteId":"sukuinage","count":1},{"kimariteId":"yorikiri","count":1},{"kimariteId":"oshidashi","count":1}]},{"rikishiId":"12169","shikona":"Onokura","rank":"Sandanme 49","wins":4,"losses":3,"winPercentage":0.5714,"kimariteBreakdown":[{"kimariteId":"hatakikomi","count":2},{"kimariteId":"yorikiri","count":1},{"kimariteId":"oshidashi","count":1}]},{"rikishiId":"12429","shikona":"Tokimaru","rank":"Sandanme 51","wins":4,"losses":3,"winPercentage":0.5714,"kimariteBreakdown":[{"kimariteId":"oshidashi","count":2},{"kimariteId":"hatakikomi","count":1},{"kimariteId":"kotenage","count":1}]},{"rikishiId":"6585","shikona":"Rendaiyama","rank":"Sandanme 52","wins":4,"losses":3,"winPercentage":0.5714,"kimariteBreakdown":[{"kimariteId":"yorikiri","count":2},{"kimariteId":"oshidashi","count":2}]},{"rikishiId":"12221","shikona":"Asakoga","rank":"Sandanme 53","wins":4,"losses":3,"winPercentage":0.5714,"kimariteBreakdown":[{"kimariteId":"hikiotoshi","count":1},{"kimariteId":"yorikiri","count":1},{"kimariteId":"shitatenage","count":1},{"kimariteId":"yoritaoshi","count":1}]},{"rikishiId":"12381","shikona":"Fujiibuki","rank":"Sandanme 57","wins":4,"losses":3,"winPercentage":0.5714,"kimariteBreakdown":[{"kimariteId":"oshidashi","count":2},{"kimariteId":"hatakikomi","count":2}]},{"rikishiId":"12006","shikona":"Dewataikai","rank":"Sandanme 59","wins":4,"losses":3,"winPercentage":0.5714,"kimariteBreakdown":[{"kimariteId":"oshidashi","count":2},{"kimariteId":"kotenage","count":1},{"kimariteId":"okuridashi","count":1}]},{"rikishiId":"12447","shikona":"Tosaeizan","rank":"Sandanme 60","wins":4,"losses":3,"winPercentage":0.5714,"kimariteBreakdown":[{"kimariteId":"oshidashi","count":2},{"kimariteId":"yoritaoshi","count":1},{"kimariteId":"kotenage","count":1}]},{"rikishiId":"12158","shikona":"Akashifuji","rank":"Sandanme 64","wins":4,"losses":3,"winPercentage":0.5714,"kimariteBreakdown":[{"kimariteId":"oshidashi","count":2},{"kimariteId":"okuritaoshi","count":1},{"kimariteId":"shitatenage","count":1}]},{"rikishiId":"2916","shikona":"Kotokino","rank":"Sandanme 68","wins":4,"losses":3,"winPercentage":0.5714,"kimariteBreakdown":[{"kimariteId":"yorikiri","count":2},{"kimariteId":"okuridashi","count":1},{"kimariteId":"oshidashi","count":1}]},{"rikishiId":"12052","shikona":"Baraki","rank":"Sandanme 68","wins":4,"losses":3,"winPercentage":0.5714,"kimariteBreakdown":[{"kimariteId":"tsukiotoshi","count":1},{"kimariteId":"yoritaoshi","count":1},{"kimariteId":"oshidashi","count":1},{"kimariteId":"hatakikomi","count":1}]},{"rikishiId":"1055","shikona":"Kasugamine","rank":"Sandanme 71","wins":4,"losses":3,"winPercentage":0.5714,"kimariteBreakdown":[{"kimariteId":"yorikiri","count":4}]},{"rikishiId":"12389","shikona":"Suio","rank":"Sandanme 71","wins":4,"losses":3,"winPercentage":0.5714,"kimariteBreakdown":[{"kimariteId":"yoritaoshi","count":2},{"kimariteId":"tsukiotoshi","count":1},{"kimariteId":"oshitaoshi","count":1}]},{"rikishiId":"12081","shikona":"Kotokantetsu","rank":"Sandanme 72","wins":4,"losses":3,"winPercentage":0.5714,"kimariteBreakdown":[{"kimariteId":"oshidashi","count":1},{"kimariteId":"sukuinage","count":1},{"kimariteId":"yoritaoshi","count":1},{"kimariteId":"uwatenage","count":1}]},{"rikishiId":"12254","shikona":"Tosashimizu","rank":"Sandanme 73","wins":4,"losses":3,"winPercentage":0.5714,"kimariteBreakdown":[{"kimariteId":"oshitaoshi","count":1},{"kimariteId":"hikiotoshi","count":1},{"kimariteId":"shitatedashinage","count":1},{"kimariteId":"yorikiri","count":1}]},{"rikishiId":"12110","shikona":"Kiritsubasa","rank":"Sandanme 75","wins":4,"losses":3,"winPercentage":0.5714,"kimariteBreakdown":[{"kimariteId":"oshidashi","count":2},{"kimariteId":"hikiotoshi","count":2}]},{"rikishiId":"5978","shikona":"Takamiryu","rank":"Sandanme 79","wins":4,"losses":3,"winPercentage":0.5714,"kimariteBreakdown":[{"kimariteId":"kotenage","count":2},{"kimariteId":"hatakikomi","count":1},{"kimariteId":"tsukiotoshi","count":1}]},{"rikishiId":"12414","shikona":"Chikuba","rank":"Sandanme 79","wins":4,"losses":3,"winPercentage":0.5714,"kimariteBreakdown":[{"kimariteId":"hatakikomi","count":1},{"kimariteId":"yorikiri","count":1},{"kimariteId":"yoritaoshi","count":1},{"kimariteId":"oshidashi","count":1}]},{"rikishiId":"1209","shikona":"Kasugaryu","rank":"Sandanme 81","wins":4,"losses":3,"winPercentage":0.5714,"kimariteBreakdown":[{"kimariteId":"shitatenage","count":1},{"kimariteId":"kakenage","count":1},{"kimariteId":"oshidashi","count":1},{"kimariteId":"tsukiotoshi","count":1}]},{"rikishiId":"11758","shikona":"Awajiumi","rank":"Sandanme 83","wins":4,"losses":3,"winPercentage":0.5714,"kimariteBreakdown":[{"kimariteId":"yoritaoshi","count":2},{"kimariteId":"yorikiri","count":1},{"kimariteId":"oshitaoshi","count":1}]},{"rikishiId":"12344","shikona":"Mochizuki","rank":"Sandanme 86","wins":4,"losses":3,"winPercentage":0.5714,"kimariteBreakdown":[{"kimariteId":"kotenage","count":1},{"kimariteId":"uwatenage","count":1},{"kimariteId":"yorikiri","count":1},{"kimariteId":"oshitaoshi","count":1}]},{"rikishiId":"12374","shikona":"Hakuomaru","rank":"Sandanme 88","wins":4,"losses":3,"winPercentage":0.5714,"kimariteBreakdown":[{"kimariteId":"hatakikomi","count":2},{"kimariteId":"uwatenage","count":1},{"kimariteId":"kubinage","count":1}]},{"rikishiId":"12196","shikona":"Iko","rank":"Sandanme 91","wins":4,"losses":3,"winPercentage":0.5714,"kimariteBreakdown":[{"kimariteId":"yorikiri","count":2},{"kimariteId":"sukuinage","count":1},{"kimariteId":"oshidashi","count":1}]},{"rikishiId":"12336","shikona":"Kaiyuma","rank":"Sandanme 92","wins":4,"losses":3,"winPercentage":0.5714,"kimariteBreakdown":[{"kimariteId":"tsukiotoshi","count":1},{"kimariteId":"katasukashi","count":1},{"kimariteId":"hatakikomi","count":1},{"kimariteId":"yorikiri","count":1}]},{"rikishiId":"11924","shikona":"Mienosato","rank":"Sandanme 94","wins":4,"losses":3,"winPercentage":0.5714,"kimariteBreakdown":[{"kimariteId":"oshitaoshi","count":1},{"kimariteId":"oshidashi","count":1},{"kimariteId":"yorikiri","count":1},{"kimariteId":"sotogake","count":1}]},{"rikishiId":"493","shikona":"Toho","rank":"Sandanme 97","wins":4,"losses":3,"winPercentage":0.5714,"kimariteBreakdown":[{"kimariteId":"yorikiri","count":2},{"kimariteId":"hikiotoshi","count":1},{"kimariteId":"uwatenage","count":1}]},{"rikishiId":"12476","shikona":"Yamenosato","rank":"Sandanme 98","wins":4,"losses":3,"winPercentage":0.5714,"kimariteBreakdown":[{"kimariteId":"hatakikomi","count":2},{"kimariteId":"yorikiri","count":1},{"kimariteId":"oshidashi","count":1}]},{"rikishiId":"12042","shikona":"Tatsunoumi","rank":"Sandanme 99","wins":3,"losses":1,"winPercentage":0.75,"kimariteBreakdown":[{"kimariteId":"hikiotoshi","count":1},{"kimariteId":"katasukashi","count":1},{"kimariteId":"hatakikomi","count":1}]},{"rikishiId":"12225","shikona":"Sazanami","rank":"Sandanme 2","wins":3,"losses":3,"winPercentage":0.5,"kimariteBreakdown":[{"kimariteId":"yorikiri","count":2},{"kimariteId":"yoritaoshi","count":1}]},{"rikishiId":"9074","shikona":"Hokutoo","rank":"Sandanme 2","wins":3,"losses":3,"winPercentage":0.5,"kimariteBreakdown":[{"kimariteId":"uwatenage","count":1},{"kimariteId":"sotogake","count":1},{"kimariteId":"yorikiri","count":1}]},{"rikishiId":"11768","shikona":"Mitotsukasa","rank":"Sandanme 4","wins":3,"losses":3,"winPercentage":0.5,"kimariteBreakdown":[{"kimariteId":"hikiotoshi","count":1},{"kimariteId":"yorikiri","count":1},{"kimariteId":"hatakikomi","count":1}]},{"rikishiId":"12174","shikona":"Sadanogo","rank":"Sandanme 95","wins":3,"losses":3,"winPercentage":0.5,"kimariteBreakdown":[{"kimariteId":"oshidashi","count":1},{"kimariteId":"yorikiri","count":1},{"kimariteId":"tsukiotoshi","count":1}]},{"rikishiId":"12373","shikona":"Tochikodai","rank":"Sandanme 5","wins":3,"losses":4,"winPercentage":0.4286,"kimariteBreakdown":[{"kimariteId":"hatakikomi","count":1},{"kimariteId":"oshidashi","count":1},{"kimariteId":"katasukashi","count":1}]},{"rikishiId":"12300","shikona":"Hokutotsubasa","rank":"Sandanme 8","wins":3,"losses":4,"winPercentage":0.4286,"kimariteBreakdown":[{"kimariteId":"yorikiri","count":1},{"kimariteId":"oshitaoshi","count":1},{"kimariteId":"hatakikomi","count":1}]},{"rikishiId":"9061","shikona":"Aoi","rank":"Sandanme 10","wins":3,"losses":4,"winPercentage":0.4286,"kimariteBreakdown":[{"kimariteId":"yorikiri","count":1},{"kimariteId":"oshidashi","count":1},{"kimariteId":"hikiotoshi","count":1}]},{"rikishiId":"12131","shikona":"Tamakongo","rank":"Sandanme 11","wins":3,"losses":4,"winPercentage":0.4286,"kimariteBreakdown":[{"kimariteId":"hatakikomi","count":2},{"kimariteId":"yoritaoshi","count":1}]},{"rikishiId":"11767","shikona":"Oginosho","rank":"Sandanme 14","wins":3,"losses":4,"winPercentage":0.4286,"kimariteBreakdown":[{"kimariteId":"hatakikomi","count":1},{"kimariteId":"koshikudake","count":1},{"kimariteId":"tsukiotoshi","count":1}]},{"rikishiId":"12436","shikona":"Tokisoma","rank":"Sandanme 17","wins":3,"losses":4,"winPercentage":0.4286,"kimariteBreakdown":[{"kimariteId":"yorikiri","count":1},{"kimariteId":"tsukiotoshi","count":1},{"kimariteId":"oshitaoshi","count":1}]},{"rikishiId":"6611","shikona":"Hisanotora","rank":"Sandanme 17","wins":3,"losses":4,"winPercentage":0.4286,"kimariteBreakdown":[{"kimariteId":"uwatedashinage","count":1},{"kimariteId":"tsukiotoshi","count":1},{"kimariteId":"oshidashi","count":1}]},{"rikishiId":"12064","shikona":"Chiyonokatsu","rank":"Sandanme 19","wins":3,"losses":4,"winPercentage":0.4286,"kimariteBreakdown":[{"kimariteId":"yorikiri","count":1},{"kimariteId":"kotenage","count":1},{"kimariteId":"oshidashi","count":1}]},{"rikishiId":"12192","shikona":"Ohata","rank":"Sandanme 20","wins":3,"losses":4,"winPercentage":0.4286,"kimariteBreakdown":[{"kimariteId":"yorikiri","count":1},{"kimariteId":"yoritaoshi","count":1},{"kimariteId":"uwatenage","count":1}]},{"rikishiId":"12299","shikona":"Hokutoryu","rank":"Sandanme 23","wins":3,"losses":4,"winPercentage":0.4286,"kimariteBreakdown":[{"kimariteId":"hatakikomi","count":1},{"kimariteId":"oshidashi","count":1},{"kimariteId":"sukuinage","count":1}]},{"rikishiId":"12432","shikona":"Shoji","rank":"Sandanme 26","wins":3,"losses":4,"winPercentage":0.4286,"kimariteBreakdown":[{"kimariteId":"tsukiotoshi","count":1},{"kimariteId":"oshidashi","count":1},{"kimariteId":"yorikiri","count":1}]},{"rikishiId":"12201","shikona":"Ryutsukasa","rank":"Sandanme 29","wins":3,"losses":4,"winPercentage":0.4286,"kimariteBreakdown":[{"kimariteId":"katasukashi","count":1},{"kimariteId":"oshidashi","count":1},{"kimariteId":"nichonage","count":1}]},{"rikishiId":"12061","shikona":"Matsuda","rank":"Sandanme 30","wins":3,"losses":4,"winPercentage":0.4286,"kimariteBreakdown":[{"kimariteId":"okuritaoshi","count":1},{"kimariteId":"oshidashi","count":1},{"kimariteId":"yorikiri","count":1}]},{"rikishiId":"12046","shikona":"Kyokushori","rank":"Sandanme 30","wins":3,"losses":4,"winPercentage":0.4286,"kimariteBreakdown":[{"kimariteId":"yorikiri","count":2},{"kimariteId":"oshidashi","count":1}]},{"rikishiId":"12137","shikona":"Kaiseijo","rank":"Sandanme 31","wins":3,"losses":4,"winPercentage":0.4286,"kimariteBreakdown":[{"kimariteId":"yorikiri","count":2},{"kimariteId":"uwatedashinage","count":1}]},{"rikishiId":"12393","shikona":"Seigo","rank":"Sandanme 34","wins":3,"losses":4,"winPercentage":0.4286,"kimariteBreakdown":[{"kimariteId":"oshidashi","count":2},{"kimariteId":"kotenage","count":1}]},{"rikishiId":"1062","shikona":"Hagane","rank":"Sandanme 37","wins":3,"losses":4,"winPercentage":0.4286,"kimariteBreakdown":[{"kimariteId":"oshidashi","count":3}]},{"rikishiId":"12347","shikona":"Tsuyukusa","rank":"Sandanme 37","wins":3,"losses":4,"winPercentage":0.4286,"kimariteBreakdown":[{"kimariteId":"tsukitaoshi","count":1},{"kimariteId":"yorikiri","count":1},{"kimariteId":"hatakikomi","count":1}]},{"rikishiId":"12021","shikona":"Ginseizan","rank":"Sandanme 39","wins":3,"losses":4,"winPercentage":0.4286,"kimariteBreakdown":[{"kimariteId":"yorikiri","count":1},{"kimariteId":"oshidashi","count":1},{"kimariteId":"tsukiotoshi","count":1}]},{"rikishiId":"12526","shikona":"Daikisho","rank":"Sandanme 41","wins":3,"losses":4,"winPercentage":0.4286,"kimariteBreakdown":[{"kimariteId":"yorikiri","count":1},{"kimariteId":"oshidashi","count":1},{"kimariteId":"hatakikomi","count":1}]},{"rikishiId":"12139","shikona":"Shuji","rank":"Sandanme 44","wins":3,"losses":4,"winPercentage":0.4286,"kimariteBreakdown":[{"kimariteId":"yorikiri","count":2},{"kimariteId":"uwatedashinage","count":1}]},{"rikishiId":"12337","shikona":"Fujisato","rank":"Sandanme 45","wins":3,"losses":4,"winPercentage":0.4286,"kimariteBreakdown":[{"kimariteId":"yoritaoshi","count":2},{"kimariteId":"yorikiri","count":1}]},{"rikishiId":"12458","shikona":"Asonoyama","rank":"Sandanme 48","wins":3,"losses":4,"winPercentage":0.4286,"kimariteBreakdown":[{"kimariteId":"yorikiri","count":1},{"kimariteId":"tsukiotoshi","count":1},{"kimariteId":"hatakikomi","count":1}]},{"rikishiId":"6578","shikona":"Teraoumi","rank":"Sandanme 50","wins":3,"losses":4,"winPercentage":0.4286,"kimariteBreakdown":[{"kimariteId":"yorikiri","count":1},{"kimariteId":"hikiotoshi","count":1},{"kimariteId":"okuridashi","count":1}]},{"rikishiId":"8904","shikona":"Homarefuji","rank":"Sandanme 52","wins":3,"losses":4,"winPercentage":0.4286,"kimariteBreakdown":[{"kimariteId":"uwatenage","count":1},{"kimariteId":"yorikiri","count":1},{"kimariteId":"tsukiotoshi","count":1}]},{"rikishiId":"497","shikona":"Koshinoryu","rank":"Sandanme 55","wins":3,"losses":4,"winPercentage":0.4286,"kimariteBreakdown":[{"kimariteId":"yorikiri","count":2},{"kimariteId":"oshidashi","count":1}]},{"rikishiId":"11837","shikona":"Azumasho","rank":"Sandanme 56","wins":3,"losses":4,"winPercentage":0.4286,"kimariteBreakdown":[{"kimariteId":"yorikiri","count":2},{"kimariteId":"uwatenage","count":1}]},{"rikishiId":"4981","shikona":"Hamaeiko","rank":"Sandanme 56","wins":3,"losses":4,"winPercentage":0.4286,"kimariteBreakdown":[{"kimariteId":"oshidashi","count":2},{"kimariteId":"abisetaoshi","count":1}]},{"rikishiId":"12119","shikona":"Genbumaru","rank":"Sandanme 59","wins":3,"losses":4,"winPercentage":0.4286,"kimariteBreakdown":[{"kimariteId":"oshidashi","count":2},{"kimariteId":"uwatedashinage","count":1}]},{"rikishiId":"12519","shikona":"Hokutomaru","rank":"Sandanme 60","wins":3,"losses":4,"winPercentage":0.4286,"kimariteBreakdown":[{"kimariteId":"oshidashi","count":1},{"kimariteId":"hatakikomi","count":1},{"kimariteId":"kimedashi","count":1}]},{"rikishiId":"12171","shikona":"Kenyu","rank":"Sandanme 61","wins":3,"losses":4,"winPercentage":0.4286,"kimariteBreakdown":[{"kimariteId":"yorikiri","count":1},{"kimariteId":"uwatedashinage","count":1},{"kimariteId":"hatakikomi","count":1}]},{"rikishiId":"12260","shikona":"Aratora","rank":"Sandanme 62","wins":3,"losses":4,"winPercentage":0.4286,"kimariteBreakdown":[{"kimariteId":"yorikiri","count":2},{"kimariteId":"oshidashi","count":1}]},{"rikishiId":"6588","shikona":"Komanokuni","rank":"Sandanme 65","wins":3,"losses":4,"winPercentage":0.4286,"kimariteBreakdown":[{"kimariteId":"yorikiri","count":3}]},{"rikishiId":"11847","shikona":"Fujitaisei","rank":"Sandanme 67","wins":3,"losses":4,"winPercentage":0.4286,"kimariteBreakdown":[{"kimariteId":"oshidashi","count":2},{"kimariteId":"uwatedashinage","count":1}]},{"rikishiId":"11953","shikona":"Oka","rank":"Sandanme 72","wins":3,"losses":4,"winPercentage":0.4286,"kimariteBreakdown":[{"kimariteId":"oshidashi","count":3}]},{"rikishiId":"12466","shikona":"Daiyusho","rank":"Sandanme 76","wins":3,"losses":4,"winPercentage":0.4286,"kimariteBreakdown":[{"kimariteId":"oshidashi","count":2},{"kimariteId":"hatakikomi","count":1}]},{"rikishiId":"12480","shikona":"Kototakuya","rank":"Sandanme 77","wins":3,"losses":4,"winPercentage":0.4286,"kimariteBreakdown":[{"kimariteId":"okuritaoshi","count":1},{"kimariteId":"hikiotoshi","count":1},{"kimariteId":"kimedashi","count":1}]},{"rikishiId":"2919","shikona":"Daishowaka","rank":"Sandanme 78","wins":3,"losses":4,"winPercentage":0.4286,"kimariteBreakdown":[{"kimariteId":"tsukidashi","count":1},{"kimariteId":"yorikiri","count":1},{"kimariteId":"okuritaoshi","count":1}]},{"rikishiId":"9104","shikona":"Takatenshu","rank":"Sandanme 80","wins":3,"losses":4,"winPercentage":0.4286,"kimariteBreakdown":[{"kimariteId":"uwatenage","count":1},{"kimariteId":"tsukiotoshi","count":1},{"kimariteId":"yorikiri","count":1}]},{"rikishiId":"11988","shikona":"Ryuo","rank":"Sandanme 81","wins":3,"losses":4,"winPercentage":0.4286,"kimariteBreakdown":[{"kimariteId":"oshitaoshi","count":2},{"kimariteId":"uwatenage","count":1}]},{"rikishiId":"11818","shikona":"Etsunohana","rank":"Sandanme 82","wins":3,"losses":4,"winPercentage":0.4286,"kimariteBreakdown":[{"kimariteId":"sotogake","count":1},{"kimariteId":"okuridashi","count":1},{"kimariteId":"yoritaoshi","count":1}]},{"rikishiId":"12241","shikona":"Akitoba","rank":"Sandanme 84","wins":3,"losses":4,"winPercentage":0.4286,"kimariteBreakdown":[{"kimariteId":"tsukidashi","count":1},{"kimariteId":"oshidashi","count":1},{"kimariteId":"uwatenage","count":1}]},{"rikishiId":"12353","shikona":"Sakurafuji","rank":"Sandanme 85","wins":3,"losses":4,"winPercentage":0.4286,"kimariteBreakdown":[{"kimariteId":"oshidashi","count":2},{"kimariteId":"okuridashi","count":1}]},{"rikishiId":"12274","shikona":"Miyanofuji","rank":"Sandanme 88","wins":3,"losses":4,"winPercentage":0.4286,"kimariteBreakdown":[{"kimariteId":"yoritaoshi","count":2},{"kimariteId":"hatakikomi","count":1}]},{"rikishiId":"12294","shikona":"Asashinjo","rank":"Sandanme 90","wins":3,"losses":4,"winPercentage":0.4286,"kimariteBreakdown":[{"kimariteId":"oshidashi","count":2},{"kimariteId":"oshitaoshi","count":1}]},{"rikishiId":"916","shikona":"Tochikasuga","rank":"Sandanme 90","wins":3,"losses":4,"winPercentage":0.4286,"kimariteBreakdown":[{"kimariteId":"okuridashi","count":2},{"kimariteId":"oshidashi","count":1}]},{"rikishiId":"11842","shikona":"Fujihisashi","rank":"Sandanme 94","wins":3,"losses":4,"winPercentage":0.4286,"kimariteBreakdown":[{"kimariteId":"oshidashi","count":2},{"kimariteId":"yorikiri","count":1}]},{"rikishiId":"12391","shikona":"Miyabishin","rank":"Sandanme 97","wins":3,"losses":4,"winPercentage":0.4286,"kimariteBreakdown":[{"kimariteId":"uwatenage","count":2},{"kimariteId":"tsukiotoshi","count":1}]},{"rikishiId":"7167","shikona":"Hamadayama","rank":"Sandanme 100","wins":3,"losses":4,"winPercentage":0.4286,"kimariteBreakdown":[{"kimariteId":"yorikiri","count":2},{"kimariteId":"hikiotoshi","count":1}]},{"rikishiId":"12173","shikona":"Ryuma","rank":"Sandanme 99","wins":2,"losses":0,"winPercentage":1,"kimariteBreakdown":[{"kimariteId":"uwatenage","count":1},{"kimariteId":"mitokorozeme","count":1}]},{"rikishiId":"12310","shikona":"Furanshisu","rank":"Sandanme 100","wins":2,"losses":0,"winPercentage":1,"kimariteBreakdown":[{"kimariteId":"yorikiri","count":1},{"kimariteId":"hatakikomi","count":1}]},{"rikishiId":"12276","shikona":"Kaishu","rank":"Sandanme 98","wins":2,"losses":2,"winPercentage":0.5,"kimariteBreakdown":[{"kimariteId":"oshitaoshi","count":1},{"kimariteId":"tsukitaoshi","count":1}]},{"rikishiId":"12087","shikona":"Yutakasho","rank":"Sandanme 1","wins":2,"losses":3,"winPercentage":0.4,"kimariteBreakdown":[{"kimariteId":"kotenage","count":1},{"kimariteId":"yoritaoshi","count":1}]},{"rikishiId":"12252","shikona":"Saionji","rank":"Sandanme 69","wins":2,"losses":4,"winPercentage":0.3333,"kimariteBreakdown":[{"kimariteId":"oshidashi","count":1},{"kimariteId":"hatakikomi","count":1}]},{"rikishiId":"12165","shikona":"Yuma","rank":"Sandanme 9","wins":2,"losses":5,"winPercentage":0.2857,"kimariteBreakdown":[{"kimariteId":"oshidashi","count":2}]},{"rikishiId":"12271","shikona":"Goshimaru","rank":"Sandanme 12","wins":2,"losses":5,"winPercentage":0.2857,"kimariteBreakdown":[{"kimariteId":"yoritaoshi","count":1},{"kimariteId":"oshidashi","count":1}]},{"rikishiId":"11925","shikona":"Kirinofuji","rank":"Sandanme 13","wins":2,"losses":5,"winPercentage":0.2857,"kimariteBreakdown":[{"kimariteId":"yorikiri","count":1},{"kimariteId":"oshidashi","count":1}]},{"rikishiId":"5954","shikona":"Asanojo","rank":"Sandanme 16","wins":2,"losses":5,"winPercentage":0.2857,"kimariteBreakdown":[{"kimariteId":"oshidashi","count":1},{"kimariteId":"yorikiri","count":1}]},{"rikishiId":"12515","shikona":"Kurohimeyama","rank":"Sandanme 18","wins":2,"losses":5,"winPercentage":0.2857,"kimariteBreakdown":[{"kimariteId":"oshidashi","count":2}]},{"rikishiId":"2836","shikona":"Katsunofuji","rank":"Sandanme 25","wins":2,"losses":5,"winPercentage":0.2857,"kimariteBreakdown":[{"kimariteId":"oshidashi","count":1},{"kimariteId":"yorikiri","count":1}]},{"rikishiId":"12155","shikona":"Kitadaichi","rank":"Sandanme 26","wins":2,"losses":5,"winPercentage":0.2857,"kimariteBreakdown":[{"kimariteId":"oshidashi","count":1},{"kimariteId":"oshitaoshi","count":1}]},{"rikishiId":"7143","shikona":"Amakaze","rank":"Sandanme 27","wins":2,"losses":5,"winPercentage":0.2857,"kimariteBreakdown":[{"kimariteId":"uwatedashinage","count":1},{"kimariteId":"shitatenage","count":1}]},{"rikishiId":"12007","shikona":"Dewanojo","rank":"Sandanme 27","wins":2,"losses":5,"winPercentage":0.2857,"kimariteBreakdown":[{"kimariteId":"uwatedashinage","count":1},{"kimariteId":"shitatenage","count":1}]},{"rikishiId":"6618","shikona":"Chiyoraizan","rank":"Sandanme 36","wins":2,"losses":5,"winPercentage":0.2857,"kimariteBreakdown":[{"kimariteId":"yorikiri","count":2}]},{"rikishiId":"12528","shikona":"Hodaka","rank":"Sandanme 40","wins":2,"losses":5,"winPercentage":0.2857,"kimariteBreakdown":[{"kimariteId":"tsukidashi","count":1},{"kimariteId":"yorikiri","count":1}]},{"rikishiId":"12338","shikona":"Wakenosato","rank":"Sandanme 41","wins":2,"losses":5,"winPercentage":0.2857,"kimariteBreakdown":[{"kimariteId":"okuridashi","count":1},{"kimariteId":"yorikiri","count":1}]},{"rikishiId":"12236","shikona":"Oyamatoumi","rank":"Sandanme 43","wins":2,"losses":5,"winPercentage":0.2857,"kimariteBreakdown":[{"kimariteId":"tsukiotoshi","count":1},{"kimariteId":"tsukidashi","count":1}]},{"rikishiId":"7160","shikona":"Ebisumaru","rank":"Sandanme 45","wins":2,"losses":5,"winPercentage":0.2857,"kimariteBreakdown":[{"kimariteId":"shitatenage","count":1},{"kimariteId":"yoritaoshi","count":1}]},{"rikishiId":"6020","shikona":"Denzan","rank":"Sandanme 53","wins":2,"losses":5,"winPercentage":0.2857,"kimariteBreakdown":[{"kimariteId":"yorikiri","count":2}]},{"rikishiId":"12134","shikona":"Tochimitsuru","rank":"Sandanme 54","wins":2,"losses":5,"winPercentage":0.2857,"kimariteBreakdown":[{"kimariteId":"oshidashi","count":2}]},{"rikishiId":"12275","shikona":"Hayanami","rank":"Sandanme 55","wins":2,"losses":5,"winPercentage":0.2857,"kimariteBreakdown":[{"kimariteId":"shitatenage","count":1},{"kimariteId":"yorikiri","count":1}]},{"rikishiId":"9078","shikona":"Ako","rank":"Sandanme 58","wins":2,"losses":5,"winPercentage":0.2857,"kimariteBreakdown":[{"kimariteId":"oshidashi","count":1},{"kimariteId":"oshitaoshi","count":1}]},{"rikishiId":"6628","shikona":"Wakahizen","rank":"Sandanme 64","wins":2,"losses":5,"winPercentage":0.2857,"kimariteBreakdown":[{"kimariteId":"kotenage","count":1},{"kimariteId":"oshidashi","count":1}]},{"rikishiId":"12359","shikona":"Wakaichiro","rank":"Sandanme 67","wins":2,"losses":5,"winPercentage":0.2857,"kimariteBreakdown":[{"kimariteId":"okuridashi","count":1},{"kimariteId":"oshidashi","count":1}]},{"rikishiId":"11888","shikona":"Hikarugenji","rank":"Sandanme 70","wins":2,"losses":5,"winPercentage":0.2857,"kimariteBreakdown":[{"kimariteId":"oshidashi","count":2}]},{"rikishiId":"12175","shikona":"Masuminato","rank":"Sandanme 74","wins":2,"losses":5,"winPercentage":0.2857,"kimariteBreakdown":[{"kimariteId":"tsukiotoshi","count":1},{"kimariteId":"shitatenage","count":1}]},{"rikishiId":"12206","shikona":"Dainichido","rank":"Sandanme 74","wins":2,"losses":5,"winPercentage":0.2857,"kimariteBreakdown":[{"kimariteId":"oshidashi","count":2}]},{"rikishiId":"12568","shikona":"Kawabuchi","rank":"Sandanme 78","wins":2,"losses":5,"winPercentage":0.2857,"kimariteBreakdown":[{"kimariteId":"oshidashi","count":1},{"kimariteId":"hatakikomi","count":1}]},{"rikishiId":"12455","shikona":"Hinataryu","rank":"Sandanme 82","wins":2,"losses":5,"winPercentage":0.2857,"kimariteBreakdown":[{"kimariteId":"yoritaoshi","count":1},{"kimariteId":"uwatenage","count":1}]},{"rikishiId":"12078","shikona":"Tsunekawa","rank":"Sandanme 83","wins":2,"losses":5,"winPercentage":0.2857,"kimariteBreakdown":[{"kimariteId":"okuridashi","count":1},{"kimariteId":"yoritaoshi","count":1}]},{"rikishiId":"9086","shikona":"Mutsukaze","rank":"Sandanme 87","wins":2,"losses":5,"winPercentage":0.2857,"kimariteBreakdown":[{"kimariteId":"okuridashi","count":1},{"kimariteId":"katasukashi","count":1}]},{"rikishiId":"12306","shikona":"Akatora","rank":"Sandanme 93","wins":2,"losses":5,"winPercentage":0.2857,"kimariteBreakdown":[{"kimariteId":"oshidashi","count":1},{"kimariteId":"hatakikomi","count":1}]},{"rikishiId":"12536","shikona":"Yoshii","rank":"Sandanme 96","wins":2,"losses":5,"winPercentage":0.2857,"kimariteBreakdown":[{"kimariteId":"sukuinage","count":2}]},{"rikishiId":"12346","shikona":"Chiyodaigo","rank":"Sandanme 10","wins":1,"losses":0,"winPercentage":1,"kimariteBreakdown":[{"kimariteId":"yorikiri","count":1}]},{"rikishiId":"12434","shikona":"Wakaryusei","rank":"Sandanme 69","wins":1,"losses":1,"winPercentage":0.5,"kimariteBreakdown":[{"kimariteId":"hikiotoshi","count":1}]},{"rikishiId":"12314","shikona":"Hiradoumi","rank":"Sandanme 3","wins":1,"losses":4,"winPercentage":0.2,"kimariteBreakdown":[{"kimariteId":"hatakikomi","count":1}]},{"rikishiId":"6647","shikona":"Oazuma","rank":"Sandanme 1","wins":1,"losses":5,"winPercentage":0.1667,"kimariteBreakdown":[{"kimariteId":"tsukidashi","count":1}]},{"rikishiId":"12319","shikona":"Kotoyusho","rank":"Sandanme 5","wins":1,"losses":5,"winPercentage":0.1667,"kimariteBreakdown":[{"kimariteId":"yorikiri","count":1}]},{"rikishiId":"12506","shikona":"Tokinohira","rank":"Sandanme 6","wins":1,"losses":6,"winPercentage":0.1429,"kimariteBreakdown":[{"kimariteId":"hatakikomi","count":1}]},{"rikishiId":"5986","shikona":"Genkaiho","rank":"Sandanme 20","wins":1,"losses":6,"winPercentage":0.1429,"kimariteBreakdown":[{"kimariteId":"oshidashi","count":1}]},{"rikishiId":"9106","shikona":"Mitozakura","rank":"Sandanme 28","wins":1,"losses":6,"winPercentage":0.1429,"kimariteBreakdown":[{"kimariteId":"yorikiri","count":1}]},{"rikishiId":"12342","shikona":"Tsushimanada","rank":"Sandanme 36","wins":1,"losses":6,"winPercentage":0.1429,"kimariteBreakdown":[{"kimariteId":"oshidashi","count":1}]},{"rikishiId":"12542","shikona":"Tokihayate","rank":"Sandanme 44","wins":1,"losses":6,"winPercentage":0.1429,"kimariteBreakdown":[{"kimariteId":"kimetaoshi","count":1}]},{"rikishiId":"1054","shikona":"Hitenryu","rank":"Sandanme 63","wins":1,"losses":6,"winPercentage":0.1429,"kimariteBreakdown":[{"kimariteId":"oshidashi","count":1}]},{"rikishiId":"12534","shikona":"Fujinoyama","rank":"Sandanme 75","wins":1,"losses":6,"winPercentage":0.1429,"kimariteBreakdown":[{"kimariteId":"uwatenage","count":1}]},{"rikishiId":"179","shikona":"Tenichi","rank":"Sandanme 91","wins":1,"losses":6,"winPercentage":0.1429,"kimariteBreakdown":[{"kimariteId":"oshidashi","count":1}]},{"rikishiId":"9098","shikona":"Sadanosato","rank":"Sandanme 4","wins":0,"losses":0,"winPercentage":0,"kimariteBreakdown":[]},{"rikishiId":"12098","shikona":"Musashikuni","rank":"Sandanme 38","wins":0,"losses":0,"winPercentage":0,"kimariteBreakdown":[]},{"rikishiId":"12050","shikona":"Kyokuyuko","rank":"Sandanme 54","wins":0,"losses":0,"winPercentage":0,"kimariteBreakdown":[]},{"rikishiId":"11984","shikona":"Tennozan","rank":"Sandanme 61","wins":0,"losses":0,"winPercentage":0,"kimariteBreakdown":[]},{"rikishiId":"11731","shikona":"Sadanoryu","rank":"Sandanme 62","wins":0,"losses":0,"winPercentage":0,"kimariteBreakdown":[]},{"rikishiId":"12399","shikona":"Akashiryu","rank":"Sandanme 87","wins":0,"losses":0,"winPercentage":0,"kimariteBreakdown":[]},{"rikishiId":"11760","shikona":"Kototaiki","rank":"Sandanme 92","wins":0,"losses":0,"winPercentage":0,"kimariteBreakdown":[]},{"rikishiId":"11886","shikona":"Fujinowaka","rank":"Sandanme 96","wins":0,"losses":5,"winPercentage":0,"kimariteBreakdown":[]},{"rikishiId":"12166","shikona":"Sadanohikari","rank":"Sandanme 46","wins":0,"losses":7,"winPercentage":0,"kimariteBreakdown":[]}]