[{"rikishiId":"176","shikona":"Narahikari","rank":"Makushita 44","wins":7,"losses":0,"winPercentage":1,"kimariteBreakdown":[{"kimariteId":"oshidashi","count":5},{"kimariteId":"yorikiri","count":2}]},{"rikishiId":"46","shikona":"Dewaarashi","rank":"Makushita 1","wins":6,"losses":1,"winPercentage":0.8571,"kimariteBreakdown":[{"kimariteId":"yorikiri","count":4},{"kimariteId":"oshidashi","count":1},{"kimariteId":"utchari","count":1}]},{"rikishiId":"102","shikona":"Asahibenten","rank":"Makushita 13","wins":6,"losses":1,"winPercentage":0.8571,"kimariteBreakdown":[{"kimariteId":"yorikiri","count":4},{"kimariteId":"tsukidashi","count":1},{"kimariteId":"oshidashi","count":1}]},{"rikishiId":"173","shikona":"Ryukai","rank":"Makushita 25","wins":6,"losses":1,"winPercentage":0.8571,"kimariteBreakdown":[{"kimariteId":"tsukiotoshi","count":2},{"kimariteId":"hatakikomi","count":1},{"kimariteId":"yorikiri","count":1},{"kimariteId":"shitatedashinage","count":1},{"kimariteId":"kubinage","count":1}]},{"rikishiId":"141","shikona":"Sakaguchi","rank":"Makushita 32","wins":6,"losses":1,"winPercentage":0.8571,"kimariteBreakdown":[{"kimariteId":"oshidashi","count":2},{"kimariteId":"hikiotoshi","count":2},{"kimariteId":"uwatenage","count":1},{"kimariteId":"shitatenage","count":1}]},{"rikishiId":"190","shikona":"Wakachikuba","rank":"Makushita 46","wins":6,"losses":1,"winPercentage":0.8571,"kimariteBreakdown":[{"kimariteId":"hikiotoshi","count":2},{"kimariteId":"oshitaoshi","count":1},{"kimariteId":"yorikiri","count":1},{"kimariteId":"oshidashi","count":1},{"kimariteId":"tsukidashi","count":1}]},{"rikishiId":"133","shikona":"Genkai","rank":"Makushita 53","wins":6,"losses":1,"winPercentage":0.8571,"kimariteBreakdown":[{"kimariteId":"yorikiri","count":2},{"kimariteId":"oshidashi","count":2},{"kimariteId":"tsukidashi","count":1},{"kimariteId":"uwatenage","count":1}]},{"rikishiId":"154","shikona":"Toshinriki","rank":"Makushita 58","wins":5,"losses":1,"winPercentage":0.8333,"kimariteBreakdown":[{"kimariteId":"yorikiri","count":2},{"kimariteId":"hatakikomi","count":1},{"kimariteId":"oshidashi","count":1},{"kimariteId":"okuridashi","count":1}]},{"rikishiId":"148","shikona":"Aoba","rank":"Makushita 50","wins":3,"losses":1,"winPercentage":0.75,"kimariteBreakdown":[{"kimariteId":"oshidashi","count":2},{"kimariteId":"nichonage","count":1}]},{"rikishiId":"124","shikona":"Sumiya","rank":"Makushita 5","wins":5,"losses":2,"winPercentage":0.7143,"kimariteBreakdown":[{"kimariteId":"yorikiri","count":2},{"kimariteId":"oshidashi","count":1},{"kimariteId":"okuridashi","count":1},{"kimariteId":"kotenage","count":1}]},{"rikishiId":"218","shikona":"Wakakinryu","rank":"Makushita 6","wins":5,"losses":2,"winPercentage":0.7143,"kimariteBreakdown":[{"kimariteId":"oshidashi","count":2},{"kimariteId":"yorikiri","count":2},{"kimariteId":"tottari","count":1}]},{"rikishiId":"147","shikona":"Toyonokuni","rank":"Makushita 8","wins":5,"losses":2,"winPercentage":0.7143,"kimariteBreakdown":[{"kimariteId":"yorikiri","count":4},{"kimariteId":"hatakikomi","count":1}]},{"rikishiId":"784","shikona":"Daishoyama","rank":"Makushita 18","wins":5,"losses":2,"winPercentage":0.7143,"kimariteBreakdown":[{"kimariteId":"hatakikomi","count":2},{"kimariteId":"oshidashi","count":1},{"kimariteId":"hikiotoshi","count":1},{"kimariteId":"okuridashi","count":1}]},{"rikishiId":"77","shikona":"Yutakafuji","rank":"Makushita 19","wins":5,"losses":2,"winPercentage":0.7143,"kimariteBreakdown":[{"kimariteId":"yorikiri","count":3},{"kimariteId":"shitatenage","count":1},{"kimariteId":"tsukiotoshi","count":1}]},{"rikishiId":"73","shikona":"Kanechika","rank":"Makushita 22","wins":5,"losses":2,"winPercentage":0.7143,"kimariteBreakdown":[{"kimariteId":"oshidashi","count":2},{"kimariteId":"tsukitaoshi","count":1},{"kimariteId":"yoritaoshi","count":1},{"kimariteId":"yorikiri","count":1}]},{"rikishiId":"371","shikona":"Kyokunankai","rank":"Makushita 26","wins":5,"losses":2,"winPercentage":0.7143,"kimariteBreakdown":[{"kimariteId":"yorikiri","count":2},{"kimariteId":"tsukidashi","count":2},{"kimariteId":"oshidashi","count":1}]},{"rikishiId":"86","shikona":"Futatsukuba","rank":"Makushita 27","wins":5,"losses":2,"winPercentage":0.7143,"kimariteBreakdown":[{"kimariteId":"okuridashi","count":1},{"kimariteId":"yorikiri","count":1},{"kimariteId":"tsukidashi","count":1},{"kimariteId":"tsukiotoshi","count":1},{"kimariteId":"sukuinage","count":1}]},{"rikishiId":"139","shikona":"Asahiumi","rank":"Makushita 30","wins":5,"losses":2,"winPercentage":0.7143,"kimariteBreakdown":[{"kimariteId":"oshidashi","count":2},{"kimariteId":"oshitaoshi","count":1},{"kimariteId":"uwatenage","count":1},{"kimariteId":"yorikiri","count":1}]},{"rikishiId":"197","shikona":"Maenowaka","rank":"Makushita 34","wins":5,"losses":2,"winPercentage":0.7143,"kimariteBreakdown":[{"kimariteId":"kirikaeshi","count":2},{"kimariteId":"kawazugake","count":1},{"kimariteId":"hatakikomi","count":1},{"kimariteId":"yorikiri","count":1}]},{"rikishiId":"300","shikona":"Dairaido","rank":"Makushita 35","wins":5,"losses":2,"winPercentage":0.7143,"kimariteBreakdown":[{"kimariteId":"oshidashi","count":2},{"kimariteId":"hikiotoshi","count":1},{"kimariteId":"okuridashi","count":1},{"kimariteId":"hatakikomi","count":1}]},{"rikishiId":"276","shikona":"Satsumanishiki","rank":"Makushita 36","wins":5,"losses":2,"winPercentage":0.7143,"kimariteBreakdown":[{"kimariteId":"hatakikomi","count":1},{"kimariteId":"yorikiri","count":1},{"kimariteId":"yoritaoshi","count":1},{"kimariteId":"shitatenage","count":1},{"kimariteId":"kotenage","count":1}]},{"rikishiId":"214","shikona":"Toshinyama","rank":"Makushita 41","wins":5,"losses":2,"winPercentage":0.7143,"kimariteBreakdown":[{"kimariteId":"yorikiri","count":2},{"kimariteId":"uwatenage","count":1},{"kimariteId":"oshitaoshi","count":1},{"kimariteId":"hatakikomi","count":1}]},{"rikishiId":"202","shikona":"Teruazuma","rank":"Makushita 42","wins":5,"losses":2,"winPercentage":0.7143,"kimariteBreakdown":[{"kimariteId":"yorikiri","count":3},{"kimariteId":"uwatenage","count":1},{"kimariteId":"shitatedashinage","count":1}]},{"rikishiId":"256","shikona":"Kotohino","rank":"Makushita 49","wins":5,"losses":2,"winPercentage":0.7143,"kimariteBreakdown":[{"kimariteId":"oshidashi","count":3},{"kimariteId":"hikiotoshi","count":2}]},{"rikishiId":"179","shikona":"Tenichi","rank":"Makushita 52","wins":5,"losses":2,"winPercentage":0.7143,"kimariteBreakdown":[{"kimariteId":"yorikiri","count":2},{"kimariteId":"oshidashi","count":2},{"kimariteId":"tsukiotoshi","count":1}]},{"rikishiId":"74","shikona":"Kotokanyu","rank":"Makushita 4","wins":4,"losses":2,"winPercentage":0.6667,"kimariteBreakdown":[{"kimariteId":"yorikiri","count":2},{"kimariteId":"yoritaoshi","count":1},{"kimariteId":"hatakikomi","count":1}]},{"rikishiId":"27","shikona":"Wakanojo","rank":"Makushita 2","wins":3,"losses":2,"winPercentage":0.6,"kimariteBreakdown":[{"kimariteId":"hikiotoshi","count":1},{"kimariteId":"yoritaoshi","count":1},{"kimariteId":"oshidashi","count":1}]},{"rikishiId":"79","shikona":"Kotoiwakuni","rank":"Makushita 3","wins":3,"losses":2,"winPercentage":0.6,"kimariteBreakdown":[{"kimariteId":"okuridashi","count":2},{"kimariteId":"shitatenage","count":1}]},{"rikishiId":"206","shikona":"Kotokasuga","rank":"Makushita 56","wins":3,"losses":2,"winPercentage":0.6,"kimariteBreakdown":[{"kimariteId":"yorikiri","count":2},{"kimariteId":"oshidashi","count":1}]},{"rikishiId":"437","shikona":"Hamakairyu","rank":"Makushita 59","wins":3,"losses":2,"winPercentage":0.6,"kimariteBreakdown":[{"kimariteId":"tsukiotoshi","count":1},{"kimariteId":"okuridashi","count":1},{"kimariteId":"hatakikomi","count":1}]},{"rikishiId":"95","shikona":"Hidenokuni","rank":"Makushita 8","wins":4,"losses":3,"winPercentage":0.5714,"kimariteBreakdown":[{"kimariteId":"yorikiri","count":2},{"kimariteId":"oshidashi","count":1},{"kimariteId":"uwatedashinage","count":1}]},{"rikishiId":"91","shikona":"Hoshiandesu","rank":"Makushita 9","wins":4,"losses":3,"winPercentage":0.5714,"kimariteBreakdown":[{"kimariteId":"yorikiri","count":2},{"kimariteId":"tsukidashi","count":1},{"kimariteId":"oshidashi","count":1}]},{"rikishiId":"99","shikona":"Shunketsu","rank":"Makushita 12","wins":4,"losses":3,"winPercentage":0.5714,"kimariteBreakdown":[{"kimariteId":"oshidashi","count":2},{"kimariteId":"yorikiri","count":1},{"kimariteId":"zubuneri","count":1}]},{"rikishiId":"80","shikona":"Otoryu","rank":"Makushita 14","wins":4,"losses":3,"winPercentage":0.5714,"kimariteBreakdown":[{"kimariteId":"kotenage","count":1},{"kimariteId":"shitatehineri","count":1},{"kimariteId":"oshidashi","count":1},{"kimariteId":"hatakikomi","count":1}]},{"rikishiId":"126","shikona":"Tochinoyama","rank":"Makushita 15","wins":4,"losses":3,"winPercentage":0.5714,"kimariteBreakdown":[{"kimariteId":"oshidashi","count":2},{"kimariteId":"tsukiotoshi","count":1},{"kimariteId":"hatakikomi","count":1}]},{"rikishiId":"175","shikona":"Ushiomaru","rank":"Makushita 16","wins":4,"losses":3,"winPercentage":0.5714,"kimariteBreakdown":[{"kimariteId":"yorikiri","count":2},{"kimariteId":"oshidashi","count":1},{"kimariteId":"hikiotoshi","count":1}]},{"rikishiId":"312","shikona":"Hokutomine","rank":"Makushita 18","wins":4,"losses":3,"winPercentage":0.5714,"kimariteBreakdown":[{"kimariteId":"uwatenage","count":2},{"kimariteId":"yorikiri","count":1},{"kimariteId":"oshidashi","count":1}]},{"rikishiId":"261","shikona":"Isshin","rank":"Makushita 19","wins":4,"losses":3,"winPercentage":0.5714,"kimariteBreakdown":[{"kimariteId":"oshidashi","count":2},{"kimariteId":"tsukidashi","count":1},{"kimariteId":"kirikaeshi","count":1}]},{"rikishiId":"131","shikona":"Karatsunada","rank":"Makushita 20","wins":4,"losses":3,"winPercentage":0.5714,"kimariteBreakdown":[{"kimariteId":"okuritaoshi","count":1},{"kimariteId":"yorikiri","count":1},{"kimariteId":"hatakikomi","count":1},{"kimariteId":"shitatenage","count":1}]},{"rikishiId":"240","shikona":"Ichinotani","rank":"Makushita 21","wins":4,"losses":3,"winPercentage":0.5714,"kimariteBreakdown":[{"kimariteId":"hatakikomi","count":2},{"kimariteId":"yorikiri","count":1},{"kimariteId":"okuridashi","count":1}]},{"rikishiId":"120","shikona":"Aranonami","rank":"Makushita 24","wins":4,"losses":3,"winPercentage":0.5714,"kimariteBreakdown":[{"kimariteId":"yorikiri","count":3},{"kimariteId":"kotenage","count":1}]},{"rikishiId":"212","shikona":"Chiyononada","rank":"Makushita 26","wins":4,"losses":3,"winPercentage":0.5714,"kimariteBreakdown":[{"kimariteId":"yorikiri","count":1},{"kimariteId":"uwatenage","count":1},{"kimariteId":"yoritaoshi","count":1},{"kimariteId":"hatakikomi","count":1}]},{"rikishiId":"68","shikona":"Gokenzan","rank":"Makushita 31","wins":4,"losses":3,"winPercentage":0.5714,"kimariteBreakdown":[{"kimariteId":"oshidashi","count":3},{"kimariteId":"shitatedashinage","count":1}]},{"rikishiId":"311","shikona":"Naminooto","rank":"Makushita 31","wins":4,"losses":3,"winPercentage":0.5714,"kimariteBreakdown":[{"kimariteId":"oshidashi","count":2},{"kimariteId":"sotogake","count":1},{"kimariteId":"oshitaoshi","count":1}]},{"rikishiId":"158","shikona":"Natsubori","rank":"Makushita 33","wins":4,"losses":3,"winPercentage":0.5714,"kimariteBreakdown":[{"kimariteId":"yorikiri","count":2},{"kimariteId":"uwatehineri","count":1},{"kimariteId":"kirikaeshi","count":1}]},{"rikishiId":"268","shikona":"Takahijiri","rank":"Makushita 34","wins":4,"losses":3,"winPercentage":0.5714,"kimariteBreakdown":[{"kimariteId":"oshidashi","count":2},{"kimariteId":"yoritaoshi","count":1},{"kimariteId":"yorikiri","count":1}]},{"rikishiId":"380","shikona":"Higo","rank":"Makushita 35","wins":4,"losses":3,"winPercentage":0.5714,"kimariteBreakdown":[{"kimariteId":"yorikiri","count":2},{"kimariteId":"kirikaeshi","count":1},{"kimariteId":"tsukiotoshi","count":1}]},{"rikishiId":"159","shikona":"Kiyonoumi","rank":"Makushita 39","wins":4,"losses":3,"winPercentage":0.5714,"kimariteBreakdown":[{"kimariteId":"oshidashi","count":2},{"kimariteId":"yorikiri","count":2}]},{"rikishiId":"146","shikona":"Fukuseyama","rank":"Makushita 41","wins":4,"losses":3,"winPercentage":0.5714,"kimariteBreakdown":[{"kimariteId":"oshidashi","count":2},{"kimariteId":"yorikiri","count":1},{"kimariteId":"hatakikomi","count":1}]},{"rikishiId":"217","shikona":"Takanoumi","rank":"Makushita 43","wins":4,"losses":3,"winPercentage":0.5714,"kimariteBreakdown":[{"kimariteId":"oshidashi","count":2},{"kimariteId":"hatakikomi","count":1},{"kimariteId":"yorikiri","count":1}]},{"rikishiId":"283","shikona":"Wakatenyu","rank":"Makushita 46","wins":4,"losses":3,"winPercentage":0.5714,"kimariteBreakdown":[{"kimariteId":"oshidashi","count":2},{"kimariteId":"uwatenage","count":1},{"kimariteId":"yorikiri","count":1}]},{"rikishiId":"865","shikona":"Kasugao","rank":"Makushita 47","wins":4,"losses":3,"winPercentage":0.5714,"kimariteBreakdown":[{"kimariteId":"yorikiri","count":2},{"kimariteId":"tsukiotoshi","count":1},{"kimariteId":"oshidashi","count":1}]},{"rikishiId":"306","shikona":"Wakayuki","rank":"Makushita 50","wins":4,"losses":3,"winPercentage":0.5714,"kimariteBreakdown":[{"kimariteId":"hatakikomi","count":1},{"kimariteId":"okuridashi","count":1},{"kimariteId":"tsukiotoshi","count":1},{"kimariteId":"oshitaoshi","count":1}]},{"rikishiId":"314","shikona":"Daihoyama","rank":"Makushita 52","wins":4,"losses":3,"winPercentage":0.5714,"kimariteBreakdown":[{"kimariteId":"oshidashi","count":1},{"kimariteId":"uwatenage","count":1},{"kimariteId":"yoritaoshi","count":1},{"kimariteId":"yorikiri","count":1}]},{"rikishiId":"216","shikona":"Raiko","rank":"Makushita 53","wins":4,"losses":3,"winPercentage":0.5714,"kimariteBreakdown":[{"kimariteId":"yorikiri","count":2},{"kimariteId":"uwatenage","count":1},{"kimariteId":"shitatenage","count":1}]},{"rikishiId":"150","shikona":"Tokinoyutaka","rank":"Makushita 55","wins":4,"losses":3,"winPercentage":0.5714,"kimariteBreakdown":[{"kimariteId":"oshidashi","count":1},{"kimariteId":"hatakikomi","count":1},{"kimariteId":"yorikiri","count":1},{"kimariteId":"okuridashi","count":1}]},{"rikishiId":"200","shikona":"Tatsukabuto","rank":"Makushita 56","wins":4,"losses":3,"winPercentage":0.5714,"kimariteBreakdown":[{"kimariteId":"yorikiri","count":2},{"kimariteId":"hikkake","count":1},{"kimariteId":"tsukiotoshi","count":1}]},{"rikishiId":"107","shikona":"Kasuganishiki","rank":"Makushita 4","wins":3,"losses":3,"winPercentage":0.5,"kimariteBreakdown":[{"kimariteId":"sukuinage","count":1},{"kimariteId":"tsukiotoshi","count":1},{"kimariteId":"hikiotoshi","count":1}]},{"rikishiId":"294","shikona":"Tachigami","rank":"Makushita 54","wins":3,"losses":3,"winPercentage":0.5,"kimariteBreakdown":[{"kimariteId":"yoritaoshi","count":1},{"kimariteId":"yorikiri","count":1},{"kimariteId":"hatakikomi","count":1}]},{"rikishiId":"787","shikona":"Keno","rank":"Makushita 55","wins":3,"losses":3,"winPercentage":0.5,"kimariteBreakdown":[{"kimariteId":"yorikiri","count":2},{"kimariteId":"yoritaoshi","count":1}]},{"rikishiId":"116","shikona":"Wakatsutomu","rank":"Makushita 7","wins":3,"losses":4,"winPercentage":0.4286,"kimariteBreakdown":[{"kimariteId":"yoritaoshi","count":1},{"kimariteId":"oshitaoshi","count":1},{"kimariteId":"kotenage","count":1}]},{"rikishiId":"92","shikona":"Harunoyama","rank":"Makushita 10","wins":3,"losses":4,"winPercentage":0.4286,"kimariteBreakdown":[{"kimariteId":"katasukashi","count":1},{"kimariteId":"hikiotoshi","count":1},{"kimariteId":"sukuinage","count":1}]},{"rikishiId":"225","shikona":"Takanotsuru","rank":"Makushita 12","wins":3,"losses":4,"winPercentage":0.4286,"kimariteBreakdown":[{"kimariteId":"yorikiri","count":2},{"kimariteId":"kainahineri","count":1}]},{"rikishiId":"75","shikona":"Daihisho","rank":"Makushita 14","wins":3,"losses":4,"winPercentage":0.4286,"kimariteBreakdown":[{"kimariteId":"yorikiri","count":1},{"kimariteId":"yoritaoshi","count":1},{"kimariteId":"oshidashi","count":1}]},{"rikishiId":"113","shikona":"Asofuji","rank":"Makushita 15","wins":3,"losses":4,"winPercentage":0.4286,"kimariteBreakdown":[{"kimariteId":"yorikiri","count":1},{"kimariteId":"yoritaoshi","count":1},{"kimariteId":"oshidashi","count":1}]},{"rikishiId":"56","shikona":"Yanagawa","rank":"Makushita 17","wins":3,"losses":4,"winPercentage":0.4286,"kimariteBreakdown":[{"kimariteId":"hatakikomi","count":1},{"kimariteId":"hikiotoshi","count":1},{"kimariteId":"yorikiri","count":1}]},{"rikishiId":"104","shikona":"Wakaazuma","rank":"Makushita 17","wins":3,"losses":4,"winPercentage":0.4286,"kimariteBreakdown":[{"kimariteId":"oshidashi","count":2},{"kimariteId":"shitatedashinage","count":1}]},{"rikishiId":"132","shikona":"Kotonomine","rank":"Makushita 20","wins":3,"losses":4,"winPercentage":0.4286,"kimariteBreakdown":[{"kimariteId":"oshidashi","count":1},{"kimariteId":"uwatedashinage","count":1},{"kimariteId":"hatakikomi","count":1}]},{"rikishiId":"100","shikona":"Shinmei","rank":"Makushita 23","wins":3,"losses":4,"winPercentage":0.4286,"kimariteBreakdown":[{"kimariteId":"kotenage","count":1},{"kimariteId":"yorikiri","count":1},{"kimariteId":"tsukidashi","count":1}]},{"rikishiId":"161","shikona":"Kotohikari","rank":"Makushita 24","wins":3,"losses":4,"winPercentage":0.4286,"kimariteBreakdown":[{"kimariteId":"yorikiri","count":1},{"kimariteId":"hikiotoshi","count":1},{"kimariteId":"yoritaoshi","count":1}]},{"rikishiId":"205","shikona":"Fujinoyama","rank":"Makushita 29","wins":3,"losses":4,"winPercentage":0.4286,"kimariteBreakdown":[{"kimariteId":"tsukiotoshi","count":1},{"kimariteId":"yorikiri","count":1},{"kimariteId":"yoritaoshi","count":1}]},{"rikishiId":"112","shikona":"Gokokuyama","rank":"Makushita 30","wins":3,"losses":4,"winPercentage":0.4286,"kimariteBreakdown":[{"kimariteId":"yorikiri","count":1},{"kimariteId":"hikkake","count":1},{"kimariteId":"hatakikomi","count":1}]},{"rikishiId":"128","shikona":"Nishikikaze","rank":"Makushita 33","wins":3,"losses":4,"winPercentage":0.4286,"kimariteBreakdown":[{"kimariteId":"shitatenage","count":2},{"kimariteId":"kotenage","count":1}]},{"rikishiId":"94","shikona":"Kimenryu","rank":"Makushita 36","wins":3,"losses":4,"winPercentage":0.4286,"kimariteBreakdown":[{"kimariteId":"yorikiri","count":2},{"kimariteId":"oshidashi","count":1}]},{"rikishiId":"296","shikona":"Yoshiazuma","rank":"Makushita 37","wins":3,"losses":4,"winPercentage":0.4286,"kimariteBreakdown":[{"kimariteId":"tsukidashi","count":1},{"kimariteId":"sukuinage","count":1},{"kimariteId":"yorikiri","count":1}]},{"rikishiId":"226","shikona":"Wakatenro","rank":"Makushita 38","wins":3,"losses":4,"winPercentage":0.4286,"kimariteBreakdown":[{"kimariteId":"hatakikomi","count":1},{"kimariteId":"uwatenage","count":1},{"kimariteId":"oshidashi","count":1}]},{"rikishiId":"125","shikona":"Munakata","rank":"Makushita 38","wins":3,"losses":4,"winPercentage":0.4286,"kimariteBreakdown":[{"kimariteId":"tsukidashi","count":1},{"kimariteId":"hikiotoshi","count":1},{"kimariteId":"uwatedashinage","count":1}]},{"rikishiId":"222","shikona":"Sumanofuji","rank":"Makushita 39","wins":3,"losses":4,"winPercentage":0.4286,"kimariteBreakdown":[{"kimariteId":"yoritaoshi","count":1},{"kimariteId":"uwatenage","count":1},{"kimariteId":"tsukidashi","count":1}]},{"rikishiId":"315","shikona":"Nadatsukasa","rank":"Makushita 40","wins":3,"losses":4,"winPercentage":0.4286,"kimariteBreakdown":[{"kimariteId":"yoritaoshi","count":1},{"kimariteId":"hikiotoshi","count":1},{"kimariteId":"yorikiri","count":1}]},{"rikishiId":"365","shikona":"Kotokuni","rank":"Makushita 42","wins":3,"losses":4,"winPercentage":0.4286,"kimariteBreakdown":[{"kimariteId":"oshidashi","count":2},{"kimariteId":"hikiotoshi","count":1}]},{"rikishiId":"194","shikona":"Kokei","rank":"Makushita 45","wins":3,"losses":4,"winPercentage":0.4286,"kimariteBreakdown":[{"kimariteId":"oshidashi","count":1},{"kimariteId":"hatakikomi","count":1},{"kimariteId":"yoritaoshi","count":1}]},{"rikishiId":"243","shikona":"Isenohana","rank":"Makushita 49","wins":3,"losses":4,"winPercentage":0.4286,"kimariteBreakdown":[{"kimariteId":"hatakikomi","count":1},{"kimariteId":"oshidashi","count":1},{"kimariteId":"uwatenage","count":1}]},{"rikishiId":"246","shikona":"Kyokutenzan","rank":"Makushita 51","wins":3,"losses":4,"winPercentage":0.4286,"kimariteBreakdown":[{"kimariteId":"yorikiri","count":2},{"kimariteId":"yoritaoshi","count":1}]},{"rikishiId":"289","shikona":"Murayoshi","rank":"Makushita 54","wins":3,"losses":4,"winPercentage":0.4286,"kimariteBreakdown":[{"kimariteId":"oshidashi","count":2},{"kimariteId":"hatakikomi","count":1}]},{"rikishiId":"398","shikona":"Chiyokanzan","rank":"Makushita 58","wins":3,"losses":4,"winPercentage":0.4286,"kimariteBreakdown":[{"kimariteId":"yorikiri","count":1},{"kimariteId":"oshidashi","count":1},{"kimariteId":"tsukiotoshi","count":1}]},{"rikishiId":"184","shikona":"Shiganoumi","rank":"Makushita 60","wins":3,"losses":4,"winPercentage":0.4286,"kimariteBreakdown":[{"kimariteId":"hikiotoshi","count":1},{"kimariteId":"oshidashi","count":1},{"kimariteId":"uwatenage","count":1}]},{"rikishiId":"70","shikona":"Kitazakura","rank":"Makushita 2","wins":2,"losses":4,"winPercentage":0.3333,"kimariteBreakdown":[{"kimariteId":"uwatenage","count":1},{"kimariteId":"kotenage","count":1}]},{"rikishiId":"244","shikona":"Ryugi","rank":"Makushita 57","wins":2,"losses":4,"winPercentage":0.3333,"kimariteBreakdown":[{"kimariteId":"yorikiri","count":2}]},{"rikishiId":"864","shikona":"Bushuyama","rank":"Makushita 25","wins":1,"losses":2,"winPercentage":0.3333,"kimariteBreakdown":[{"kimariteId":"okuridashi","count":1}]},{"rikishiId":"118","shikona":"Fujiryu","rank":"Makushita 6","wins":2,"losses":5,"winPercentage":0.2857,"kimariteBreakdown":[{"kimariteId":"okuridashi","count":1},{"kimariteId":"yorikiri","count":1}]},{"rikishiId":"149","shikona":"Juzan","rank":"Makushita 7","wins":2,"losses":5,"winPercentage":0.2857,"kimariteBreakdown":[{"kimariteId":"kotenage","count":1},{"kimariteId":"hikiotoshi","count":1}]},{"rikishiId":"106","shikona":"Torafusuyama","rank":"Makushita 16","wins":2,"losses":5,"winPercentage":0.2857,"kimariteBreakdown":[{"kimariteId":"oshitaoshi","count":1},{"kimariteId":"shitatenage","count":1}]},{"rikishiId":"69","shikona":"Towanoyama","rank":"Makushita 21","wins":2,"losses":5,"winPercentage":0.2857,"kimariteBreakdown":[{"kimariteId":"oshidashi","count":1},{"kimariteId":"yoritaoshi","count":1}]},{"rikishiId":"119","shikona":"Takamihana","rank":"Makushita 23","wins":2,"losses":5,"winPercentage":0.2857,"kimariteBreakdown":[{"kimariteId":"oshidashi","count":1},{"kimariteId":"yorikiri","count":1}]},{"rikishiId":"180","shikona":"Wakainami","rank":"Makushita 27","wins":2,"losses":5,"winPercentage":0.2857,"kimariteBreakdown":[{"kimariteId":"oshidashi","count":1},{"kimariteId":"uwatenage","count":1}]},{"rikishiId":"61","shikona":"Hokutohikari","rank":"Makushita 28","wins":2,"losses":5,"winPercentage":0.2857,"kimariteBreakdown":[{"kimariteId":"hatakikomi","count":1},{"kimariteId":"tsukiotoshi","count":1}]},{"rikishiId":"66","shikona":"Wakahayato","rank":"Makushita 28","wins":2,"losses":5,"winPercentage":0.2857,"kimariteBreakdown":[{"kimariteId":"yoritaoshi","count":2}]},{"rikishiId":"134","shikona":"Fukuzono","rank":"Makushita 29","wins":2,"losses":5,"winPercentage":0.2857,"kimariteBreakdown":[{"kimariteId":"yorikiri","count":1},{"kimariteId":"ipponzeoi","count":1}]},{"rikishiId":"287","shikona":"Wakatoba","rank":"Makushita 37","wins":2,"losses":5,"winPercentage":0.2857,"kimariteBreakdown":[{"kimariteId":"uwatenage","count":1},{"kimariteId":"oshidashi","count":1}]},{"rikishiId":"136","shikona":"Dewanosato","rank":"Makushita 40","wins":2,"losses":5,"winPercentage":0.2857,"kimariteBreakdown":[{"kimariteId":"kimedashi","count":1},{"kimariteId":"uwatenage","count":1}]},{"rikishiId":"879","shikona":"Tooyama","rank":"Makushita 43","wins":2,"losses":5,"winPercentage":0.2857,"kimariteBreakdown":[{"kimariteId":"hatakikomi","count":1},{"kimariteId":"tsukitaoshi","count":1}]},{"rikishiId":"250","shikona":"Shindo","rank":"Makushita 48","wins":2,"losses":5,"winPercentage":0.2857,"kimariteBreakdown":[{"kimariteId":"oshidashi","count":2}]},{"rikishiId":"122","shikona":"Daimanazuru","rank":"Makushita 51","wins":2,"losses":5,"winPercentage":0.2857,"kimariteBreakdown":[{"kimariteId":"hikiotoshi","count":1},{"kimariteId":"yorikiri","count":1}]},{"rikishiId":"101","shikona":"Dewanofuji","rank":"Makushita 57","wins":2,"losses":5,"winPercentage":0.2857,"kimariteBreakdown":[{"kimariteId":"yorikiri","count":1},{"kimariteId":"oshidashi","count":1}]},{"rikishiId":"230","shikona":"Kiyoazuma","rank":"Makushita 59","wins":2,"losses":5,"winPercentage":0.2857,"kimariteBreakdown":[{"kimariteId":"oshidashi","count":1},{"kimariteId":"yorikiri","count":1}]},{"rikishiId":"171","shikona":"Tsuchihashi","rank":"Makushita 60","wins":1,"losses":3,"winPercentage":0.25,"kimariteBreakdown":[{"kimariteId":"hatakikomi","count":1}]},{"rikishiId":"84","shikona":"Tomikaze","rank":"Makushita 3","wins":1,"losses":4,"winPercentage":0.2,"kimariteBreakdown":[{"kimariteId":"oshidashi","count":1}]},{"rikishiId":"874","shikona":"Hamanishiki","rank":"Makushita 5","wins":1,"losses":5,"winPercentage":0.1667,"kimariteBreakdown":[{"kimariteId":"okuridashi","count":1}]},{"rikishiId":"82","shikona":"Tochitenko","rank":"Makushita 45","wins":1,"losses":5,"winPercentage":0.1667,"kimariteBreakdown":[{"kimariteId":"yoritaoshi","count":1}]},{"rikishiId":"168","shikona":"Hokutoiwa","rank":"Makushita 47","wins":1,"losses":5,"winPercentage":0.1667,"kimariteBreakdown":[{"kimariteId":"hatakikomi","count":1}]},{"rikishiId":"878","shikona":"Asashoryu","rank":"Makushita 9","wins":1,"losses":6,"winPercentage":0.1429,"kimariteBreakdown":[{"kimariteId":"yorikiri","count":1}]},{"rikishiId":"130","shikona":"Kaido","rank":"Makushita 11","wins":1,"losses":6,"winPercentage":0.1429,"kimariteBreakdown":[{"kimariteId":"yoritaoshi","count":1}]},{"rikishiId":"785","shikona":"Furuichi","rank":"Makushita 11","wins":1,"losses":6,"winPercentage":0.1429,"kimariteBreakdown":[{"kimariteId":"oshitaoshi","count":1}]},{"rikishiId":"151","shikona":"Ranbo","rank":"Makushita 44","wins":1,"losses":6,"winPercentage":0.1429,"kimariteBreakdown":[{"kimariteId":"kotenage","count":1}]},{"rikishiId":"67","shikona":"Tochinofuji","rank":"Makushita 48","wins":1,"losses":6,"winPercentage":0.1429,"kimariteBreakdown":[{"kimariteId":"oshitaoshi","count":1}]},{"rikishiId":"65","shikona":"Dewataira","rank":"Makushita 1","wins":0,"losses":0,"winPercentage":0,"kimariteBreakdown":[]},{"rikishiId":"24","shikona":"Ganyu","rank":"Makushita 10","wins":0,"losses":0,"winPercentage":0,"kimariteBreakdown":[]},{"rikishiId":"145","shikona":"Kobo","rank":"Makushita 13","wins":0,"losses":0,"winPercentage":0,"kimariteBreakdown":[]},{"rikishiId":"199","shikona":"Kuniazuma","rank":"Makushita 22","wins":0,"losses":7,"winPercentage":0,"kimariteBreakdown":[]},{"rikishiId":"135","shikona":"Hokutoriki","rank":"Makushita 32","wins":0,"losses":0,"winPercentage":0,"kimariteBreakdown":[]}]